Changelog
MANIFEST.in
README.md
setup.py
version_template
./devflow/__init__.py
./devflow/autopkg.py
./devflow/flow.py
./devflow/ui.py
./devflow/utils.py
./devflow/version.py
./devflow/versioning.py
devflow/__init__.py
devflow/autopkg.py
devflow/flow.py
devflow/ui.py
devflow/utils.py
devflow/version.py
devflow/versioning.py
devflow.egg-info/PKG-INFO
devflow.egg-info/SOURCES.txt
devflow.egg-info/dependency_links.txt
devflow.egg-info/entry_points.txt
devflow.egg-info/requires.txt
devflow.egg-info/top_level.txt