Metadata-Version: 1.1
Name: devflow
Version: 0.13
Summary: A set of tools to ease versioning and use of git flow.
Home-page: http://www.synnefo.org/
Author: Synnefo development team
Author-email: synnefo-devel@googlegroups.com
License: BSD
Platform: UNKNOWN
Classifier: Environment :: Console
Classifier: License :: OSI Approved :: BSD License
Classifier: Programming Language :: Python
Classifier: Programming Language :: Python :: 2 :: Only
Classifier: Topic :: Software Development
Classifier: Topic :: Software Development :: Build Tools
